censys_platform/__init__.py
censys_platform/_hooks/__init__.py
censys_platform/_hooks/sdkhooks.py
censys_platform/_hooks/types.py
censys_platform/_version.py
censys_platform/account_management.py
censys_platform/basesdk.py
censys_platform/collections.py
censys_platform/global_data.py
censys_platform/httpclient.py
censys_platform/models/__init__.py
censys_platform/models/activemq.py
censys_platform/models/alternativequery.py
censys_platform/models/amqp.py
censys_platform/models/amqp_protocol.py
censys_platform/models/amqp_version.py
censys_platform/models/analyticscapabilities.py
censys_platform/models/anyconnect.py
censys_platform/models/assetcertificatelistinputbody.py
censys_platform/models/assethostlistinputbody.py
censys_platform/models/assetwebpropertylistinputbody.py
censys_platform/models/asteriskmanagerinterface.py
censys_platform/models/attribute.py
censys_platform/models/auth.py
censys_platform/models/authenticationerror.py
censys_platform/models/authenticationerrordetail.py
censys_platform/models/authorityinfoaccess.py
censys_platform/models/autonomoussystem.py
censys_platform/models/autoreplenishconfig.py
censys_platform/models/bacnet.py
censys_platform/models/basicconstraints.py
censys_platform/models/cabforganizationid.py
censys_platform/models/capabilities.py
censys_platform/models/certificate.py
censys_platform/models/certificate_parsed.py
censys_platform/models/certificateasset.py
censys_platform/models/certificateextensions.py
censys_platform/models/certificatepolicy.py
censys_platform/models/certificaterevocation.py
censys_platform/models/certificaterevocation_revocationinfo.py
censys_platform/models/checkpointtopology.py
censys_platform/models/chromecast.py
censys_platform/models/chromecast_application.py
censys_platform/models/chromecast_namespace.py
censys_platform/models/chromecast_volume.py
censys_platform/models/chromedevtools.py
censys_platform/models/chromedevtools_target.py
censys_platform/models/ciscoipsla.py
censys_platform-0.12.1.dist-info/METADATA
censys_platform-0.12.1.dist-info/WHEEL
censys_platform-0.12.1.dist-info/RECORD
